prosperity3submit/__init__.py
prosperity3submit/__main__.py
prosperity3submit/py.typed
prosperity3submit/submit.py
prosperity3submit-0.1.1.dist-info/licenses/LICENSE
prosperity3submit-0.1.1.dist-info/METADATA
prosperity3submit-0.1.1.dist-info/WHEEL
prosperity3submit-0.1.1.dist-info/entry_points.txt
prosperity3submit-0.1.1.dist-info/top_level.txt
prosperity3submit-0.1.1.dist-info/RECORD
