Metadata-Version: 2.4
Name: prosperity3submit
Version: 0.1.1
Summary: Command-line submitter for IMC Prosperity 3 algorithms
Author-email: Jasper van Merle <jaspervmerle@gmail.com>
License: MIT License
Project-URL: Repository, https://github.com/jmerle/imc-prosperity-3-submitter
Project-URL: Issues, https://github.com/jmerle/imc-prosperity-3-submitter/issues
Project-URL: Changelog, https://github.com/jmerle/imc-prosperity-3-submitter/releases
Keywords: imc,prosperity,submit,submitter
Classifier: Development Status :: 4 - Beta
Classifier: Intended Audience :: Developers
Classifier: Intended Audience :: Financial and Insurance Industry
Classifier: License :: OSI Approved :: MIT License
Classifier: Programming Language :: Python :: 3
Requires-Python: >=3.9
License-File: LICENSE
Requires-Dist: keyring>=25.6.0
Requires-Dist: prosperity3bt>=0.2.0
Requires-Dist: requests>=2.32.3
Requires-Dist: requests-toolbelt>=1.0.0
Requires-Dist: typer>=0.15.2
Dynamic: license-file
